housekeeping/__init__.py
housekeeping/_version.py
housekeeping/base.py
housekeeping/classes.py
housekeeping/functions.py
housekeeping/helpers.py
housekeeping/modules.py
housekeeping/py.typed
housekeeping/tests/__init__.py
housekeeping/tests/test_classes.py
housekeeping/tests/test_functions.py
housekeeping/tests/test_modules.py
housekeeping/tests/testcases.py
housekeeping-1.1.dist-info/LICENSE
housekeeping-1.1.dist-info/METADATA
housekeeping-1.1.dist-info/WHEEL
housekeeping-1.1.dist-info/top_level.txt
housekeeping-1.1.dist-info/RECORD
