Metadata-Version: 2.1
Name: housekeeping
Version: 1.1
Summary: Python utilities for helping deprecate and remove code.
Author-email: "Beanbag, Inc." <questions@beanbaginc.com>
License: MIT
Project-URL: homepage, https://github.com/beanbaginc/housekeeping
Project-URL: documentation, https://github.com/beanbaginc/housekeeping
Project-URL: repository, https://github.com/beanbaginc/housekeeping
Keywords: deprecation,cleanup,code quality
Classifier: Development Status :: 5 - Production/Stable
Classifier: Environment :: Other Environment
Classifier: Intended Audience :: Developers
Classifier: License :: OSI Approved :: MIT License
Classifier: Operating System :: OS Independent
Classifier: Programming Language :: Python
Classifier: Programming Language :: Python :: 3
Classifier: Programming Language :: Python :: 3.7
Classifier: Programming Language :: Python :: 3.8
Classifier: Programming Language :: Python :: 3.9
Classifier: Programming Language :: Python :: 3.10
Classifier: Programming Language :: Python :: 3.11
Classifier: Topic :: Software Development
Classifier: Topic :: Software Development :: Libraries
Classifier: Topic :: Software Development :: Libraries :: Python Modules
Requires-Python: >=3.7
License-File: LICENSE
Requires-Dist: typing-extensions (>=4.4)
